weather_utsav/__init__.py
weather_utsav-1.0.0.dist-info/METADATA
weather_utsav-1.0.0.dist-info/WHEEL
weather_utsav-1.0.0.dist-info/top_level.txt
weather_utsav-1.0.0.dist-info/RECORD
