Metadata-Version: 2.1
Name: weather-utsav
Version: 1.0.0
Summary: This is a Weather Provider.
Home-page: UNKNOWN
Author: Utsav
Author-email: UNKNOWN
License: UNKNOWN
Platform: UNKNOWN
Requires-Dist: requests
